aws_authenticator/__init__.py
aws_authenticator/__init__.pyi
aws_authenticator/__main__.py
aws_authenticator/__main__.pyi
aws_authenticator-2024.1.0.1.dist-info/METADATA
aws_authenticator-2024.1.0.1.dist-info/WHEEL
aws_authenticator-2024.1.0.1.dist-info/RECORD
