Metadata-Version: 2.1
Name: aws_authenticator
Version: 2024.1.0.1
Summary: Login to AWS using CLI named profiles, IAM access key credentials, or SSO.
Home-page: https://gitlab.com/fer1035_python/modules/pypi-aws_authenticator
License: GPL-2.0-only
Keywords: AWS,login,profile,access key,SSO
Author: Ahmad Ferdaus Abd Razak
Author-email: ahmad.ferdaus.abd.razak@ni.com
Requires-Python: >=3.6,<4.0
Classifier: License :: OSI Approved :: GNU General Public License v2 (GPLv2)
Classifier: Programming Language :: Python :: 3
Classifier: Programming Language :: Python :: 3.6
Classifier: Programming Language :: Python :: 3.7
Classifier: Programming Language :: Python :: 3.8
Classifier: Programming Language :: Python :: 3.9
Classifier: Programming Language :: Python :: 3.10
Classifier: Programming Language :: Python :: 3.11
Classifier: Programming Language :: Python :: 3.12
Requires-Dist: aws-ssooidc (>=2021.1.1.1,<2022.0.0.0)
Requires-Dist: boto3 (>=1.17.78,<2.0.0)
Project-URL: Repository, https://gitlab.com/fer1035_python/modules/pypi-aws_authenticator
